README.txt
install.bat
setup.py
setup_egg.py
version.txt
geolocator/INSTALL.txt
geolocator/README.txt
geolocator/__init__.py
geolocator/config.py
geolocator/geolocator.py
geolocator/gislib.py
geolocator/interfaces.py
geolocator/version.txt
geolocator.egg-info/PKG-INFO
geolocator.egg-info/top_level.txt
geolocator/providers/__init__.py
geolocator/providers/countrycoordinatecsv.py
geolocator/providers/dummy.py
geolocator/providers/gns.py
geolocator/providers/maxmind.py
geolocator/tests/__init__.py
geolocator/tests/dummytests.py
geolocator/tests/geolocatortests.py
geolocator/tests/gislibtests.py
geolocator/tests/maxmindtests.py
geolocator/tests/runtests.py
geolocator/data/README.txt
geolocator/data/countrycoordinates.csv
geolocator/docs/gislib.odg
geolocator/providers/README.txt
geolocator/providers/__init__.py
geolocator/providers/countrycoordinatecsv.py
geolocator/providers/dummy.py
geolocator/providers/gns.py
geolocator/providers/maxmind.py
geolocator/tests/__init__.py
geolocator/tests/dummytests.py
geolocator/tests/geolocatortests.py
geolocator/tests/gislibtests.py
geolocator/tests/maxmindtests.py
geolocator/tests/runtests.py
