Metadata-Version: 1.0
Name: geolocator
Version: 0.1.1
Summary: geolocator library: locate places and calculate distances between them
Home-page: http://geolocator.fairsay.com
Author: Petri Savolainen
Author-email: petri.savolainen@iki.fi
License: http://www.fsf.org/licensing/licenses/lgpl.txt
Platform: any
Classifier: Development Status :: 3 - Alpha
Classifier: Intended Audience :: Developers
Classifier: License :: OSI Approved :: GNU Library or Lesser General Public License (LGPL)
Classifier: Programming Language :: Python
Classifier: Topic :: Scientific/Engineering :: GIS
Classifier: Topic :: Software Development :: Libraries :: Python Modules
Classifier: Topic :: Software Development :: Libraries
Classifier: Operating System :: Microsoft :: Windows
Classifier: Operating System :: Unix
Classifier: Operating System :: POSIX
